odoo/addons/sale_pricelist_discount_decimal_precision/README.rst
odoo/addons/sale_pricelist_discount_decimal_precision/__init__.py
odoo/addons/sale_pricelist_discount_decimal_precision/__manifest__.py
odoo/addons/sale_pricelist_discount_decimal_precision/i18n/es.po
odoo/addons/sale_pricelist_discount_decimal_precision/i18n/it.po
odoo/addons/sale_pricelist_discount_decimal_precision/i18n/sale_pricelist_discount_decimal_precision.pot
odoo/addons/sale_pricelist_discount_decimal_precision/models/__init__.py
odoo/addons/sale_pricelist_discount_decimal_precision/models/pricelist_item.py
odoo/addons/sale_pricelist_discount_decimal_precision/readme/CONTRIBUTORS.rst
odoo/addons/sale_pricelist_discount_decimal_precision/readme/DESCRIPTION.rst
odoo/addons/sale_pricelist_discount_decimal_precision/readme/USAGE.rst
odoo/addons/sale_pricelist_discount_decimal_precision/static/description/icon.png
odoo/addons/sale_pricelist_discount_decimal_precision/static/description/index.html
odoo14_addon_sale_pricelist_discount_decimal_precision-14.0.1.0.2.dev7.dist-info/METADATA
odoo14_addon_sale_pricelist_discount_decimal_precision-14.0.1.0.2.dev7.dist-info/WHEEL
odoo14_addon_sale_pricelist_discount_decimal_precision-14.0.1.0.2.dev7.dist-info/top_level.txt
odoo14_addon_sale_pricelist_discount_decimal_precision-14.0.1.0.2.dev7.dist-info/RECORD
